README.rst
earthlingtwo.zip
screenshot01.png
setup.py
docs/HISTORY.txt
plonetheme/__init__.py
plonetheme.earthlingtwo.egg-info/PKG-INFO
plonetheme.earthlingtwo.egg-info/SOURCES.txt
plonetheme.earthlingtwo.egg-info/dependency_links.txt
plonetheme.earthlingtwo.egg-info/entry_points.txt
plonetheme.earthlingtwo.egg-info/namespace_packages.txt
plonetheme.earthlingtwo.egg-info/requires.txt
plonetheme.earthlingtwo.egg-info/top_level.txt
plonetheme/earthlingtwo/__init__.py
plonetheme/earthlingtwo/configure.zcml
plonetheme/earthlingtwo/theme/earthlingtwo/index.html
plonetheme/earthlingtwo/theme/earthlingtwo/license.txt
plonetheme/earthlingtwo/theme/earthlingtwo/manifest.cfg
plonetheme/earthlingtwo/theme/earthlingtwo/rules.xml
plonetheme/earthlingtwo/theme/earthlingtwo/static/style.css
plonetheme/earthlingtwo/theme/earthlingtwo/static/images/img01.jpg
plonetheme/earthlingtwo/theme/earthlingtwo/static/images/img02.jpg
plonetheme/earthlingtwo/theme/earthlingtwo/static/images/img03.jpg
plonetheme/earthlingtwo/theme/earthlingtwo/static/images/img04.jpg
plonetheme/earthlingtwo/theme/earthlingtwo/static/images/img05.jpg
plonetheme/earthlingtwo/theme/earthlingtwo/static/images/img06.jpg
plonetheme/earthlingtwo/theme/earthlingtwo/static/images/img07.jpg
plonetheme/earthlingtwo/theme/earthlingtwo/static/images/img08.jpg
plonetheme/earthlingtwo/theme/earthlingtwo/static/images/img09.jpg
plonetheme/earthlingtwo/theme/earthlingtwo/static/images/img10.gif
plonetheme/earthlingtwo/theme/earthlingtwo/static/images/img11.gif
plonetheme/earthlingtwo/theme/earthlingtwo/static/images/img12.jpg
plonetheme/earthlingtwo/theme/earthlingtwo/static/images/img15.jpg