Metadata-Version: 1.0
Name: plonetheme.earthlingtwo
Version: 0.1
Summary: An installable Diazo theme for Plone 4.1
Home-page: http://pypi.python.org/pypi/plone.earthlingtwo
Author: Andrew Mleczko
Author-email: amleczko@redturtle.it
License: UNKNOWN
Keywords: web zope plone theme diazo
Platform: UNKNOWN
Classifier: Framework :: Plone
Classifier: Programming Language :: Python
